[
  {
    "id": "method-cement-mixing",
    "name": "水泥土搅拌桩",
    "category": "复合地基",
    "description": "通过深层搅拌机械将水泥浆与地基土强制搅拌，形成水泥土桩体",
    "applicableConditions": [
      "软土地区",
      "含水量>30%",
      "有机质含量<5%",
      "pH>4"
    ],
    "advantages": [
      "施工速度快",
      "造价较低",
      "无振动噪音",
      "可充分利用原土"
    ],
    "disadvantages": [
      "强度较低",
      "深度受限",
      "质量控制难",
      "受土质影响大"
    ],
    "designPoints": [
      "桩径500-700mm",
      "桩间距1.0-1.5m",
      "水泥掺入比15%-20%",
      "桩长进入持力层≥1m"
    ],
    "keywords": ["搅拌桩", "水泥土", "复合地基", "软土"],
    "source": "地基处理手册第6章"
  },
  {
    "id": "method-cfg-pile",
    "name": "CFG桩",
    "category": "复合地基",
    "description": "由水泥、粉煤灰、碎石、石屑加水拌和形成的高粘结强度桩",
    "applicableConditions": [
      "承载力要求较高",
      "沉降控制严格",
      "地质条件较好",
      "需要较高强度"
    ],
    "advantages": [
      "承载力高",
      "沉降小",
      "施工速度快",
      "适用范围广"
    ],
    "disadvantages": [
      "造价较高",
      "需要大型设备",
      "可能产生挤土效应",
      "检测要求高"
    ],
    "designPoints": [
      "桩径400-600mm",
      "桩间距1.5-2.5m",
      "桩长进入持力层≥1m",
      "混凝土强度C15-C25"
    ],
    "keywords": ["CFG桩", "复合地基", "承载力", "沉降"],
    "source": "地基处理手册第5章"
  },
  {
    "id": "method-preloading",
    "name": "堆载预压法",
    "category": "预压法",
    "description": "在软土地基上堆载，使地基土排水固结，提高承载力",
    "applicableConditions": [
      "软土地区",
      "有充足堆载材料",
      "工期允许",
      "需要提高承载力"
    ],
    "advantages": [
      "效果好",
      "造价较低",
      "施工简单",
      "无噪音振动"
    ],
    "disadvantages": [
      "工期长",
      "需要大量堆载",
      "可能产生不均匀沉降",
      "需要监测"
    ],
    "designPoints": [
      "堆载高度根据沉降计算确定",
      "预压时间3-6个月",
      "设置排水板",
      "做好沉降监测"
    ],
    "keywords": ["堆载", "预压", "软土", "固结"],
    "source": "地基处理手册第3章"
  },
  {
    "id": "method-dynamic-compaction",
    "name": "强夯法",
    "category": "夯实法",
    "description": "利用重锤从高处自由落下，对地基土进行强力夯实",
    "applicableConditions": [
      "碎石土、砂土",
      "低饱和度粉土、黏性土",
      "杂填土",
      "需要提高承载力"
    ],
    "advantages": [
      "效果显著",
      "造价较低",
      "施工简单",
      "适用范围广"
    ],
    "disadvantages": [
      "振动噪音大",
      "深度受限",
      "可能扰动周边",
      "受地下水影响"
    ],
    "designPoints": [
      "夯击能1000-8000kN·m",
      "夯点间距3-6m",
      "夯击次数3-10击",
      "最后两击平均夯沉量≤50mm"
    ],
    "keywords": ["强夯", "夯实", "地基处理", "承载力"],
    "source": "地基处理手册第6章"
  },
  {
    "id": "method-grouting",
    "name": "注浆法",
    "category": "注浆法",
    "description": "将浆液注入地基土中，填充孔隙、胶结土颗粒，提高地基强度",
    "applicableConditions": [
      "需要提高强度",
      "需要止水防渗",
      "有空洞需要填充",
      "地质条件复杂"
    ],
    "advantages": [
      "适用范围广",
      "效果显著",
      "施工灵活",
      "可处理复杂地层"
    ],
    "disadvantages": [
      "质量控制难",
      "造价较高",
      "可能污染环境",
      "需要专业设备"
    ],
    "designPoints": [
      "注浆压力0.2-1.0MPa",
      "浆液配比根据土质确定",
      "注浆孔间距1.0-2.0m",
      "注浆量根据计算确定"
    ],
    "keywords": ["注浆", "浆液", "地基处理", "加固"],
    "source": "地基处理手册第8章"
  }
]
